mdsynthesis/__init__.py
mdsynthesis/attach.py
mdsynthesis/filesystem.py
mdsynthesis/limbs.py
mdsynthesis/treants.py
mdsynthesis/backends/__init__.py
mdsynthesis/backends/statefiles.py
mdsynthesis/tests/__init__.py
mdsynthesis/tests/test_filesystem.py
mdsynthesis/tests/test_treants.py
mdsynthesis-0.6.1.dist-info/DESCRIPTION.rst
mdsynthesis-0.6.1.dist-info/METADATA
mdsynthesis-0.6.1.dist-info/RECORD
mdsynthesis-0.6.1.dist-info/WHEEL
mdsynthesis-0.6.1.dist-info/metadata.json
mdsynthesis-0.6.1.dist-info/top_level.txt
