Metadata-Version: 2.0
Name: mdsynthesis
Version: 0.6.1
Summary: a persistence engine for molecular dynamics data
Home-page: http://mdsynthesis.readthedocs.org/
Author: David Dotson
Author-email: dotsdl@gmail.com
License: GPL 2
Platform: UNKNOWN
Classifier: Development Status :: 3 - Alpha
Classifier: Environment :: Console
Classifier: Intended Audience :: Science/Research
Classifier: License :: OSI Approved :: GNU General Public License v2 (GPLv2)
Classifier: Operating System :: POSIX
Classifier: Programming Language :: Python
Classifier: Topic :: Scientific/Engineering
Classifier: Topic :: Software Development :: Libraries :: Python Modules
Requires-Dist: MDAnalysis (>=0.14.0)
Requires-Dist: datreant.core (>=0.6.0)
Requires-Dist: datreant.data (>=0.6.0)
